orbithunter/__init__.py
orbithunter/clipping.py
orbithunter/continuation.py
orbithunter/core.py
orbithunter/gluing.py
orbithunter/io.py
orbithunter/machine_learning.py
orbithunter/optimize.py
orbithunter/persistent_homology.py
orbithunter/shadowing.py
orbithunter/ks/__init__.py
orbithunter/ks/orbits.py
orbithunter/ks/physics.py
orbithunter-1.3.3.dist-info/LICENSE.txt
orbithunter-1.3.3.dist-info/METADATA
orbithunter-1.3.3.dist-info/WHEEL
orbithunter-1.3.3.dist-info/top_level.txt
orbithunter-1.3.3.dist-info/RECORD
